boxball_schemas/__init__.py
boxball_schemas/baseballdatabank.py
boxball_schemas/retrosheet.py
boxball_schemas-0.0.8.dist-info/METADATA
boxball_schemas-0.0.8.dist-info/WHEEL
boxball_schemas-0.0.8.dist-info/top_level.txt
boxball_schemas-0.0.8.dist-info/RECORD
