Metadata-Version: 2.1
Name: boxball-schemas
Version: 0.0.8
Summary: Schemas for the Boxball project that can be used for extension or code completion
Home-page: https://github.com/droher/boxball
Author: David Roher
Requires-Python: >=3.6
Requires-Dist: sqlalchemy >=1.3.3
